[
	{
		"__TYPE__": "SharedSliceContent",
		"variation": "default",
		"primary": {
			"button_text": {
				"__TYPE__": "FieldContent",
				"type": "Text",
				"value": "Basolski"
			},
			"button_link": {
				"key": "4ed0df9e-45ae-44d7-8e05-42a96ad6c105",
				"__TYPE__": "LinkContent",
				"value": {
					"__TYPE__": "ExternalLink",
					"url": "https://slicemachine.dev",
					"text": "dirty"
				}
			},
			"heading": {
				"__TYPE__": "StructuredTextContent",
				"value": [
					{
						"type": "heading2",
						"content": {
							"text": "Kowalski",
							"spans": []
						},
						"direction": "ltr"
					}
				]
			}
		},
		"items": []
	}
]